fycore_sdk.py
fycore/__init__.py
fycore/pyarmor_runtime_000000/__init__.py
fycore/pyarmor_runtime_000000/pyarmor_runtime.pyd
pyarmor_runtime_000000/__init__.py
pyarmor_runtime_000000/pyarmor_runtime.pyd
pyarmor_runtime_000000/linux_x86_64/pyarmor_runtime.so
pyarmor_runtime_000000/windows_x86_64/pyarmor_runtime.pyd
fycore_sdk-1.0.2.dist-info/LICENSE.md
fycore_sdk-1.0.2.dist-info/METADATA
fycore_sdk-1.0.2.dist-info/WHEEL
fycore_sdk-1.0.2.dist-info/top_level.txt
fycore_sdk-1.0.2.dist-info/RECORD
