Metadata-Version: 2.1
Name: fycore-sdk
Version: 1.0.2
Summary: Consciousness-aware AI orchestration SDK built on the CCFy framework (PyArmor protected).
Home-page: https://github.com/fthynn/fycore-sdk
Author: Fatih Yenen
Author-email: research@sonra.art
License: Proprietary
Project-URL: Source, https://github.com/fthynn/fycore-sdk
Project-URL: Tracker, https://github.com/fthynn/fycore-sdk/issues
Keywords: ai artificial-intelligence sdk agents orchestration multi-agent llm framework consciousness ccfy fycore
Classifier: Programming Language :: Python :: 3
Classifier: Programming Language :: Python :: Implementation :: CPython
Classifier: Programming Language :: Python :: 3 :: Only
Classifier: Operating System :: OS Independent
Classifier: Intended Audience :: Developers
Classifier: Topic :: Scientific/Engineering :: Artificial Intelligence
Classifier: License :: Other/Proprietary License
Requires-Python: >=3.10
License-File: LICENSE.md
Provides-Extra: dev
Requires-Dist: build>=1.0.0; extra == "dev"
Requires-Dist: twine>=5.0.0; extra == "dev"
